pyMyweblog/__init__.py
pyMyweblog/client.py
pymyweblog-0.5.4.dist-info/licenses/LICENSE
pymyweblog-0.5.4.dist-info/METADATA
pymyweblog-0.5.4.dist-info/WHEEL
pymyweblog-0.5.4.dist-info/top_level.txt
pymyweblog-0.5.4.dist-info/RECORD
