Metadata-Version: 2.4
Name: pyMyweblog
Version: 0.5.4
Summary: A Python library for interacting with the MyWebLog API
Author-email: Marcus Karlsson <marcus.karlsson@usa.net>
License: MIT License
Project-URL: Homepage, https://github.com/faanskit/pyMyweblog
Project-URL: Repository, https://github.com/faanskit/pyMyweblog
Project-URL: Issues, https://github.com/faanskit/pyMyweblog/issues
Classifier: Development Status :: 4 - Beta
Classifier: Intended Audience :: Developers
Classifier: License :: OSI Approved :: MIT License
Classifier: Operating System :: OS Independent
Classifier: Programming Language :: Python :: 3
Classifier: Programming Language :: Python :: 3.8
Classifier: Programming Language :: Python :: 3.9
Classifier: Programming Language :: Python :: 3.10
Classifier: Programming Language :: Python :: 3.11
Classifier: Topic :: Software Development :: Libraries :: Python Modules
Requires-Python: >=3.8
License-File: LICENSE
Requires-Dist: aiohttp>=3.8.0
Provides-Extra: dev
Requires-Dist: pytest; extra == "dev"
Requires-Dist: flake8; extra == "dev"
Requires-Dist: black; extra == "dev"
Dynamic: license-file
